hypervoxelate/setup.py
hypervoxelate.egg-info/PKG-INFO
hypervoxelate.egg-info/SOURCES.txt
hypervoxelate.egg-info/dependency_links.txt
hypervoxelate.egg-info/not-zip-safe
hypervoxelate.egg-info/top_level.txt